{
  "books": [
    {
      "id": "1",
      "title": "The Great Gatsby",
      "author": "F. Scott Fitzgerald",
      "isbn": "978-0-7432-7356-5",
      "genre": "Classic Literature",
      "publicationYear": 1925,
      "description": "A classic American novel set in the Jazz Age, exploring themes of wealth, love, and the American Dream through the eyes of narrator Nick Carraway.",
      "availability": "available",
      "coverUrl": "https://images.unsplash.com/photo-1544947950-fa07a98d237f?w=200&h=300&fit=crop&crop=center",
      "pages": 180,
      "publisher": "Scribner",
      "rating": 4.2
    },
    {
      "id": "2",
      "title": "To Kill a Mockingbird",
      "author": "Harper Lee",
      "isbn": "978-0-06-112008-4",
      "genre": "Classic Literature",
      "publicationYear": 1960,
      "description": "A gripping tale of racial injustice and childhood innocence in the American South, told through the eyes of Scout Finch.",
      "availability": "checked-out",
      "coverUrl": "https://images.unsplash.com/photo-1481627834876-b7833e8f5570?w=200&h=300&fit=crop&crop=center",
      "pages": 376,
      "publisher": "J.B. Lippincott & Co.",
      "rating": 4.5
    },
    {
      "id": "3",
      "title": "1984",
      "author": "George Orwell",
      "isbn": "978-0-452-28423-4",
      "genre": "Science Fiction",
      "publicationYear": 1949,
      "description": "A dystopian social science fiction novel about totalitarian control and surveillance in a future society.",
      "availability": "available",
      "coverUrl": "https://images.unsplash.com/photo-1495640388908-05fa85288e61?w=200&h=300&fit=crop&crop=center",
      "pages": 328,
      "publisher": "Secker & Warburg",
      "rating": 4.4
    },
    {
      "id": "4",
      "title": "Pride and Prejudice",
      "author": "Jane Austen",
      "isbn": "978-0-14-143951-8",
      "genre": "Romance",
      "publicationYear": 1813,
      "description": "A romantic novel that critiques the British landed gentry at the end of the 18th century through the relationship between Elizabeth Bennet and Mr. Darcy.",
      "availability": "available",
      "coverUrl": "https://images.unsplash.com/photo-1507003211169-0a1dd7228f2d?w=200&h=300&fit=crop&crop=center",
      "pages": 432,
      "publisher": "T. Egerton",
      "rating": 4.3
    },
    {
      "id": "5",
      "title": "The Catcher in the Rye",
      "author": "J.D. Salinger",
      "isbn": "978-0-316-76948-0",
      "genre": "Coming of Age",
      "publicationYear": 1951,
      "description": "A controversial novel about teenage rebellion and alienation, following Holden Caulfield's experiences in New York City.",
      "availability": "available",
      "coverUrl": "https://images.unsplash.com/photo-1512820790803-83ca734da794?w=200&h=300&fit=crop&crop=center",
      "pages": 277,
      "publisher": "Little, Brown and Company",
      "rating": 3.8
    },
    {
      "id": "6",
      "title": "Harry Potter and the Philosopher's Stone",
      "author": "J.K. Rowling",
      "isbn": "978-0-7475-3269-9",
      "genre": "Fantasy",
      "publicationYear": 1997,
      "description": "The first book in the Harry Potter series, following a young wizard's journey at Hogwarts School of Witchcraft and Wizardry.",
      "availability": "checked-out",
      "coverUrl": "https://images.unsplash.com/photo-1518373714866-3f1478910cc0?w=200&h=300&fit=crop&crop=center",
      "pages": 223,
      "publisher": "Bloomsbury",
      "rating": 4.7
    },
    {
      "id": "7",
      "title": "The Lord of the Rings",
      "author": "J.R.R. Tolkien",
      "isbn": "978-0-544-00341-5",
      "genre": "Fantasy",
      "publicationYear": 1954,
      "description": "An epic high fantasy novel about the quest to destroy the One Ring and defeat the Dark Lord Sauron.",
      "availability": "available",
      "coverUrl": "https://images.unsplash.com/photo-1589998059171-988d887df646?w=200&h=300&fit=crop&crop=center",
      "pages": 1216,
      "publisher": "Allen & Unwin",
      "rating": 4.6
    },
    {
      "id": "8",
      "title": "The Hitchhiker's Guide to the Galaxy",
      "author": "Douglas Adams",
      "isbn": "978-0-345-39180-3",
      "genre": "Science Fiction",
      "publicationYear": 1979,
      "description": "A comedic science fiction series following Arthur Dent's adventures through space after Earth's destruction.",
      "availability": "available",
      "coverUrl": "https://images.unsplash.com/photo-1446776653964-20c1d3a81b06?w=200&h=300&fit=crop&crop=center",
      "pages": 224,
      "publisher": "Pan Books",
      "rating": 4.2
    },
    {
      "id": "9",
      "title": "Dune",
      "author": "Frank Herbert",
      "isbn": "978-0-441-17271-9",
      "genre": "Science Fiction",
      "publicationYear": 1965,
      "description": "A science fiction epic set on the desert planet Arrakis, exploring politics, religion, and ecology in a distant future.",
      "availability": "available",
      "coverUrl": "/dune-book-cover-sci-fi.jpg",
      "pages": 688,
      "publisher": "Chilton Books",
      "rating": 4.3
    },
    {
      "id": "10",
      "title": "The Handmaid's Tale",
      "author": "Margaret Atwood",
      "isbn": "978-0-385-49081-8",
      "genre": "Dystopian Fiction",
      "publicationYear": 1985,
      "description": "A dystopian novel set in a totalitarian society where women's rights have been stripped away and fertility is controlled by the state.",
      "availability": "checked-out",
      "coverUrl": "https://images.unsplash.com/photo-1481627834876-b7833e8f5570?w=200&h=300&fit=crop&crop=center",
      "pages": 311,
      "publisher": "McClelland & Stewart",
      "rating": 4.1
    },
    {
      "id": "11",
      "title": "Brave New World",
      "author": "Aldous Huxley",
      "isbn": "978-0-06-085052-4",
      "genre": "Science Fiction",
      "publicationYear": 1932,
      "description": "A dystopian novel exploring a future society driven by technology, conditioning, and artificial happiness.",
      "availability": "available",
      "coverUrl": "https://images.unsplash.com/photo-1507003211169-0a1dd7228f2d?w=200&h=300&fit=crop&crop=center",
      "pages": 268,
      "publisher": "Chatto & Windus",
      "rating": 4.0
    },
    {
      "id": "12",
      "title": "The Alchemist",
      "author": "Paulo Coelho",
      "isbn": "978-0-06-231500-7",
      "genre": "Philosophy",
      "publicationYear": 1988,
      "description": "A philosophical novel about a young shepherd's journey to find treasure and discover his personal legend.",
      "availability": "available",
      "coverUrl": "https://images.unsplash.com/photo-1544947950-fa07a98d237f?w=200&h=300&fit=crop&crop=center",
      "pages": 163,
      "publisher": "HarperCollins",
      "rating": 3.9
    },
    {
      "id": "13",
      "title": "Atomic Habits",
      "author": "James Clear",
      "isbn": "978-0-7352-1129-2",
      "genre": "Self-Help",
      "publicationYear": 2018,
      "description": "A comprehensive guide to building good habits and breaking bad ones through small, incremental changes.",
      "availability": "available",
      "coverUrl": "/atomic-habits-inspired-cover.png",
      "pages": 320,
      "publisher": "Avery",
      "rating": 4.8
    },
    {
      "id": "14",
      "title": "The Midnight Library",
      "author": "Matt Haig",
      "isbn": "978-0-525-55948-1",
      "genre": "Contemporary Fiction",
      "publicationYear": 2020,
      "description": "A thought-provoking novel about life's infinite possibilities, following Nora Seed as she explores alternate versions of her life.",
      "availability": "available",
      "coverUrl": "/midnight-library-cover.png",
      "pages": 288,
      "publisher": "Viking",
      "rating": 4.2
    },
    {
      "id": "15",
      "title": "Educated",
      "author": "Tara Westover",
      "isbn": "978-0-399-59050-4",
      "genre": "Biography",
      "publicationYear": 2018,
      "description": "A powerful memoir about education, family, and the struggle between loyalty and independence.",
      "availability": "available",
      "coverUrl": "https://images.unsplash.com/photo-1481627834876-b7833e8f5570?w=200&h=300&fit=crop&crop=center",
      "pages": 334,
      "publisher": "Random House",
      "rating": 4.6
    },
    {
      "id": "16",
      "title": "The Seven Husbands of Evelyn Hugo",
      "author": "Taylor Jenkins Reid",
      "isbn": "978-1-5011-3981-2",
      "genre": "Historical Fiction",
      "publicationYear": 2017,
      "description": "A captivating novel about a reclusive Hollywood icon who finally decides to tell her story to an unknown journalist.",
      "availability": "checked-out",
      "coverUrl": "https://images.unsplash.com/photo-1507003211169-0a1dd7228f2d?w=200&h=300&fit=crop&crop=center",
      "pages": 400,
      "publisher": "Atria Books",
      "rating": 4.5
    },
    {
      "id": "17",
      "title": "Where the Crawdads Sing",
      "author": "Delia Owens",
      "isbn": "978-0-7352-1909-0",
      "genre": "Mystery",
      "publicationYear": 2018,
      "description": "A mystery and coming-of-age story set in the marshes of North Carolina, following the life of Kya Clark.",
      "availability": "available",
      "coverUrl": "https://images.unsplash.com/photo-1495640388908-05fa85288e61?w=200&h=300&fit=crop&crop=center",
      "pages": 384,
      "publisher": "G.P. Putnam's Sons",
      "rating": 4.4
    },
    {
      "id": "18",
      "title": "The Silent Patient",
      "author": "Alex Michaelides",
      "isbn": "978-1-2501-3018-4",
      "genre": "Thriller",
      "publicationYear": 2019,
      "description": "A psychological thriller about a woman who refuses to speak after allegedly murdering her husband.",
      "availability": "available",
      "coverUrl": "https://images.unsplash.com/photo-1512820790803-83ca734da794?w=200&h=300&fit=crop&crop=center",
      "pages": 336,
      "publisher": "Celadon Books",
      "rating": 4.1
    },
    {
      "id": "19",
      "title": "Becoming",
      "author": "Michelle Obama",
      "isbn": "978-1-5247-6313-8",
      "genre": "Biography",
      "publicationYear": 2018,
      "description": "An intimate and inspiring memoir by the former First Lady of the United States.",
      "availability": "available",
      "coverUrl": "https://images.unsplash.com/photo-1518373714866-3f1478910cc0?w=200&h=300&fit=crop&crop=center",
      "pages": 448,
      "publisher": "Crown Publishing",
      "rating": 4.7
    },
    {
      "id": "20",
      "title": "The Subtle Art of Not Giving a F*ck",
      "author": "Mark Manson",
      "isbn": "978-0-06-245771-4",
      "genre": "Self-Help",
      "publicationYear": 2016,
      "description": "A counterintuitive approach to living a good life through accepting negative experiences and focusing on what truly matters.",
      "availability": "available",
      "coverUrl": "https://images.unsplash.com/photo-1589998059171-988d887df646?w=200&h=300&fit=crop&crop=center",
      "pages": 224,
      "publisher": "HarperOne",
      "rating": 4.0
    }
  ]
}
